ekey_bionyxpy/__init__.py
ekey_bionyxpy/auth.py
ekey_bionyxpy/models.py
ekey_bionyxpy/py.typed
ekey_bionyxpy-1.0.1.dist-info/licenses/LICENSE
ekey_bionyxpy-1.0.1.dist-info/METADATA
ekey_bionyxpy-1.0.1.dist-info/WHEEL
ekey_bionyxpy-1.0.1.dist-info/top_level.txt
ekey_bionyxpy-1.0.1.dist-info/RECORD
