Metadata-Version: 2.4
Name: ekey-bionyxpy
Version: 1.0.1
Summary: Interact with the bionyx third party API of the ekey biometric systems.
Project-URL: Repository, https://github.com/richardpolzer/ekey-bionyx-api
Project-URL: Issues, https://github.com/richardpolzer/ekey-bionyx-api/issues
Classifier: License :: OSI Approved :: MIT License
Classifier: Topic :: Home Automation
Classifier: Programming Language :: Python
Classifier: Programming Language :: Python :: 3.11
Classifier: Programming Language :: Python :: 3.12
Requires-Python: >=3.11
License-File: LICENSE
Requires-Dist: aiohttp
Dynamic: license-file
